cordctl/__init__.py
cordctl/cli.py
cordctl/commands/__init__.py
cordctl/commands/create_channels.py
cordctl/commands/embed.py
cordctl/commands/handle_roles.py
cordctl/commands/list.py
cordctl/commands/login.py
cordctl/commands/play_music.py
cordctl/commands/welcome.py
cordctl/core/__init__.py
cordctl/core/auth.py
cordctl/core/clients.py
cordctl/core/discord_api.py
cordctl/core/utils.py
cordctl/gui/embed_gui.py
cordctl/gui/welcomer_gui.py
cordctl-0.0.2.dist-info/METADATA
cordctl-0.0.2.dist-info/WHEEL
cordctl-0.0.2.dist-info/entry_points.txt
cordctl-0.0.2.dist-info/top_level.txt
cordctl-0.0.2.dist-info/RECORD
